kpcpu.cpython-38-x86_64-linux-gnu.so
kpcpu-0.0.5.dist-info/METADATA
kpcpu-0.0.5.dist-info/WHEEL
kpcpu-0.0.5.dist-info/top_level.txt
kpcpu-0.0.5.dist-info/RECORD
